{
  "trip": {
    "title": "신혼여행계획",
    "couple": "윤경&병현",
    "route": "마드리드>바르셀로나>이스탄불",
    "startDate": "2027-04-25",
    "endDate": "2027-05-04",
    "budget": 10000000,
    "currency": "KRW"
  },
  "github": {
    "repoUrl": "https://github.com/sotoran712/SStravel",
    "branch": "main",
    "dataPath": "trip-data.json"
  },
  "itinerary": [
    {
      "id": "itn-barcelona-0428-train",
      "date": "2027-04-28",
      "time": "10:00",
      "type": "transport",
      "title": "마드리드에서 바르셀로나 이동",
      "destination": "Madrid Atocha Station",
      "address": "Madrid Atocha Railway Station, Madrid, Spain",
      "budget": 0,
      "spent": 0,
      "status": "planned",
      "note": "아토차역에서 바르셀로나로 기차 이동. 약 2시간 30분 소요, 첫차 6:30 전후부터 막차 21:00 전후까지 운행. 트립닷컴 또는 SpainRail.com 예매 메모."
    },
    {
      "id": "itn-barcelona-0428-stay",
      "date": "2027-04-28",
      "time": "15:00",
      "type": "stay",
      "title": "바르셀로나 숙소 체크인",
      "destination": "요즘사람들",
      "address": "95MC+3G7 Barcelona, Spain",
      "budget": 1100000,
      "spent": 1037984,
      "status": "reserved",
      "note": "4박 숙소. 1박 평균 259,496원. 까딸루냐 광장, 에스파냐 광장, 호텔 레기나 후보 위치 메모 및 바르셀로나 도시세 별도 납부 필요."
    },
    {
      "id": "itn-barcelona-0428-boqueria",
      "date": "2027-04-28",
      "time": "17:00",
      "type": "tour",
      "title": "라 보케리아 시장 가볍게 둘러보기",
      "destination": "La Boqueria Market",
      "address": "Mercat de la Boqueria, La Rambla, Barcelona, Spain",
      "budget": 0,
      "spent": 0,
      "status": "planned",
      "note": "다음날 가우디 투어를 위해 많이 걷지 않고 충분히 쉬는 일정으로 배치."
    },
    {
      "id": "itn-barcelona-0429-gaudi",
      "date": "2027-04-29",
      "time": "09:00",
      "type": "tour",
      "title": "가우디 투어",
      "destination": "Basilica de la Sagrada Familia",
      "address": "Basilica de la Sagrada Familia, Barcelona, Spain",
      "budget": 0,
      "spent": 0,
      "status": "planned",
      "note": "마이리얼트립 한민철 가이드 메모. 오전 가우디 투어, 구엘공원 동반 입장, 야경투어 할인 확인."
    },
    {
      "id": "itn-barcelona-0429-gothic",
      "date": "2027-04-29",
      "time": "16:00",
      "type": "tour",
      "title": "고딕지구 산책",
      "destination": "Gothic Quarter",
      "address": "Gothic Quarter, Barcelona, Spain",
      "budget": 0,
      "spent": 0,
      "status": "planned",
      "note": "낮과 밤 분위기가 달라 시간대별 산책 가능. 지하철 Zone 1, 카드 하나로 여러 명 사용 가능 메모."
    },
    {
      "id": "itn-barcelona-0429-elglop",
      "date": "2027-04-29",
      "time": "19:30",
      "type": "food",
      "title": "엘그롬 El Glop 식사 후보",
      "destination": "El Glop",
      "address": "El Glop, Barcelona, Spain",
      "budget": 0,
      "spent": 0,
      "status": "planned",
      "note": "가우디 투어 후 식사 후보."
    },
    {
      "id": "itn-barcelona-0430-bread",
      "date": "2027-04-30",
      "time": "09:30",
      "type": "food",
      "title": "보른지구 베이커리 후보",
      "destination": "Hofmann Bakery",
      "address": "Hofmann Bakery, Barcelona, Spain",
      "budget": 0,
      "spent": 0,
      "status": "planned",
      "note": "Hofmann, Joncake 베이커리 후보. 빵과 카페 중심으로 여유 있게 시작."
    },
    {
      "id": "itn-barcelona-0430-shopping",
      "date": "2027-04-30",
      "time": "11:30",
      "type": "shopping",
      "title": "디자인샵과 소품샵 둘러보기",
      "destination": "Metro Cuadrado",
      "address": "Metro Cuadrado, Barcelona, Spain",
      "budget": 0,
      "spent": 0,
      "status": "planned",
      "note": "Metro Cuadrado 디자인샵, Petritxol xocoa 추러스 후보, Bubo 초콜릿, La Chinata 무화과 발사믹·올리브오일·핸드크림 선물 후보."
    },
    {
      "id": "itn-barcelona-0430-cafe-park",
      "date": "2027-04-30",
      "time": "14:30",
      "type": "tour",
      "title": "카페와 공원 휴식",
      "destination": "Nomad Coffee",
      "address": "Nomad Coffee, Barcelona, Spain",
      "budget": 0,
      "spent": 0,
      "status": "planned",
      "note": "Nomad Coffee 테이크아웃 후 공원에서 쉬기. 구엘공원 산책 후보."
    },
    {
      "id": "itn-barcelona-0430-sunset",
      "date": "2027-04-30",
      "time": "18:30",
      "type": "tour",
      "title": "사그랏 코르 성당 일몰",
      "destination": "Temple of the Sacred Heart of Jesus",
      "address": "Temple of the Sacred Heart of Jesus, Barcelona, Spain",
      "budget": 0,
      "spent": 0,
      "status": "planned",
      "note": "일몰 포인트 후보. 당일 컨디션에 따라 이동."
    },
    {
      "id": "itn-barcelona-0430-casalolea",
      "date": "2027-04-30",
      "time": "20:00",
      "type": "food",
      "title": "Casa Lolea Barcelona 저녁 후보",
      "destination": "Casa Lolea Barcelona",
      "address": "Casa Lolea Barcelona, Barcelona, Spain",
      "budget": 0,
      "spent": 0,
      "status": "planned",
      "note": "화이트 트러플 파스타 후보. 예약 필요 여부 확인."
    },
    {
      "id": "itn-barcelona-0501-raval",
      "date": "2027-05-01",
      "time": "11:00",
      "type": "tour",
      "title": "바르셀로나 자유 일정",
      "destination": "MACBA",
      "address": "Museu d'Art Contemporani de Barcelona, Barcelona, Spain",
      "budget": 0,
      "spent": 0,
      "status": "planned",
      "note": "바르셀로나 현대미술관 앞길에서 라발지구 방향으로 내려오는 동선. 전날 쇼핑·관광 강도에 따라 자유롭게 조정."
    }
  ],
  "flights": [
    {
      "id": "flt-1781710292960-b39e97a8e6464",
      "airline": "터키항공",
      "flightNumber": "TK091",
      "route": "ICN>MAD",
      "departureDate": "2027-04-25",
      "bookingRef": "",
      "budget": 2300000,
      "spent": 2234800
    }
  ],
  "stays": [
    {
      "id": "stay-1781709944022-fd05a538b57a9",
      "name": "아스파시오스 소피아 아파트먼트",
      "address": "Rda. de Valencia, 1, Arganzuela, 28012 Madrid, 스페인",
      "checkIn": "2027-04-25",
      "checkOut": "2027-04-27",
      "budget": 600000,
      "spent": 544054
    },
    {
      "id": "stay-1781710041444-0d0b0385e1cb78",
      "name": "요즘사람들",
      "address": "95MC+3G7 바르셀로나 스페인",
      "checkIn": "2027-04-28",
      "checkOut": "2027-05-02",
      "budget": 1100000,
      "spent": 1037984
    },
    {
      "id": "stay-1781710147527-8c1e703b2cae98",
      "name": "카라코이 이스탄불",
      "address": "Müeyyedzade, Kemeraltı Cd. No: 10, Beyoglu, 34425",
      "checkIn": "2027-05-02",
      "checkOut": "2027-05-04",
      "budget": 260000,
      "spent": 289322
    }
  ],
  "checklist": [
    {
      "id": "chk-1",
      "label": "여권 만료일 확인",
      "done": false
    },
    {
      "id": "chk-4",
      "label": "여행자 보험 증권",
      "done": false
    }
  ]
}
